Workbook

Sheet Simulador
B2: 🪙🤲 SIMULADOR DE INVESTIMENTOS EM FIIs
B5: CONFIGURAÇÕES E PARÂMETROS | E5: RESULTADOS CHAVE
B6: Salário Mensal | C6: 5000 | E6: Quanto investir por mês? | F6: =C8 -> 800
B7: Sugestão de Aporte (30%) | C7: =C6*0.3 -> 1500 | E7: Por quantos anos? | F7: =C10 -> 12
B8: Aporte Mensal Efetivo | C8: 800 | E8: Qual a taxa de rendimento mensal? | F8: =C9 -> 0.008
B9: Rendimento Mensal Esperado (% a.m.) | C9: 0.008 | E9: Quanto de patrimônio vai acumular? | F9: =FV(C9, C10*12, -C8, 0) -> 215004.4
B10: Prazo Simulado (Anos) | C10: 12 | E10: Quanto vai receber de dividendos por mês? | F10: =F9*C9 -> 1720.0352
B11: Perfil do Investidor | C11: Conservador
B13: PROJEÇÃO DE CENÁRIOS
B14: Anos | C14: Meses | D14: Patrimônio Acumulado | E14: Dividendos Mensais Estimados
B15: 2 | C15: =B15*12 -> 24 | D15: =FV($C$9, C15, -$C$8, 0) -> 21074.524 | E15: =D15*$C$9 -> 168.59619
B16: 5 | C16: =B16*12 -> 60 | D16: =FV($C$9, C16, -$C$8, 0) -> 61299.093 | E16: =D16*$C$9 -> 490.39275
B17: 10 | C17: =B17*12 -> 120 | D17: =FV($C$9, C17, -$C$8, 0) -> 160173.98 | E17: =D17*$C$9 -> 1281.3918
B18: 20 | C18: =B18*12 -> 240 | D18: =FV($C$9, C18, -$C$8, 0) -> 576904.98 | E18: =D18*$C$9 -> 4615.2398
B19: 30 | C19: =B19*12 -> 360 | D19: =FV($C$9, C19, -$C$8, 0) -> 1661130.6 | E19: =D19*$C$9 -> 13289.045
B21: DIVISÃO DO APORTE POR TIPO DE FUNDO
B22: Tipo de Fundo | C22: Alocação (%) | D22: Aporte Mensal (R$) | E22: Patrimônio Projetado (R$)
B23: FIIs de Papel | C23: =VLOOKUP($C$11&"_"&B23, Apoio!$C$2:$D$19, 2, FALSE) -> 0.4 | D23: =$C$8*C23 -> 320 | E23: =$F$9*C23 -> 86001.761
B24: FIIs de Tijolo - Logística | C24: =VLOOKUP($C$11&"_"&B24, Apoio!$C$2:$D$19, 2, FALSE) -> 0.25 | D24: =$C$8*C24 -> 200 | E24: =$F$9*C24 -> 53751.101
B25: FIIs de Tijolo - Lajes Corporativas | C25: =VLOOKUP($C$11&"_"&B25, Apoio!$C$2:$D$19, 2, FALSE) -> 0.1 | D25: =$C$8*C25 -> 80 | E25: =$F$9*C25 -> 21500.44
B26: FIIs de Tijolo - Shopping | C26: =VLOOKUP($C$11&"_"&B26, Apoio!$C$2:$D$19, 2, FALSE) -> 0.1 | D26: =$C$8*C26 -> 80 | E26: =$F$9*C26 -> 21500.44
B27: FIIs de Fondos de Fondos (FOFs) | C27: =VLOOKUP($C$11&"_"&B27, Apoio!$C$2:$D$19, 2, FALSE) -> 0.1 | D27: =$C$8*C27 -> 80 | E27: =$F$9*C27 -> 21500.44
B28: FIIs do Agronegócio (Fiagro) | C28: =VLOOKUP($C$11&"_"&B28, Apoio!$C$2:$D$19, 2, FALSE) -> 0.05 | D28: =$C$8*C28 -> 40 | E28: =$F$9*C28 -> 10750.22
B30: CENÁRIO COMPARATIVO: APORTE SUGERIDO (30%)
B31: Métrica | C31: Aporte Sugerido | D31: Aporte Atual | E31: Diferença
B32: Valor do Aporte | C32: =C6*0.3 -> 1500 | D32: =C8 -> 800 | E32: =C32-D32 -> 700
B33: Patrimônio Projetado | C33: =FV(C9, C10*12, -C32, 0) -> 403133.26 | D33: =F9 -> 215004.4 | E33: =C33-D33 -> 188128.85
B34: Dividendos Mensais | C34: =C33*C9 -> 3225.066 | D34: =F10 -> 1720.0352 | E34: =C34-D34 -> 1505.0308

Sheet Apoio
A1: Perfil | B1: Tipo de Fundo | C1: Chave Composta | D1: Percentual
A2: Conservador | B2: FIIs de Papel | C2: Conservador_FIIs de Papel | D2: 0.4
A3: Conservador | B3: FIIs de Tijolo - Logística | C3: Conservador_FIIs de Tijolo - Logística | D3: 0.25
A4: Conservador | B4: FIIs de Tijolo - Lajes Corporativas | C4: Conservador_FIIs de Tijolo - Lajes Corporativas | D4: 0.1
A5: Conservador | B5: FIIs de Tijolo - Shopping | C5: Conservador_FIIs de Tijolo - Shopping | D5: 0.1
A6: Conservador | B6: FIIs de Fondos de Fondos (FOFs) | C6: Conservador_FIIs de Fondos de Fondos (FOFs) | D6: 0.1
A7: Conservador | B7: FIIs do Agronegócio (Fiagro) | C7: Conservador_FIIs do Agronegócio (Fiagro) | D7: 0.05
A8: Moderado | B8: FIIs de Papel | C8: Moderado_FIIs de Papel | D8: 0.25
A9: Moderado | B9: FIIs de Tijolo - Logística | C9: Moderado_FIIs de Tijolo - Logística | D9: 0.25
A10: Moderado | B10: FIIs de Tijolo - Lajes Corporativas | C10: Moderado_FIIs de Tijolo - Lajes Corporativas | D10: 0.15
A11: Moderado | B11: FIIs de Tijolo - Shopping | C11: Moderado_FIIs de Tijolo - Shopping | D11: 0.15
A12: Moderado | B12: FIIs de Fondos de Fondos (FOFs) | C12: Moderado_FIIs de Fondos de Fondos (FOFs) | D12: 0.1
A13: Moderado | B13: FIIs do Agronegócio (Fiagro) | C13: Moderado_FIIs do Agronegócio (Fiagro) | D13: 0.1
... A19: Arrojado | B19: FIIs do Agronegócio (Fiagro) | C19: Arrojado_FIIs do Agronegócio (Fiagro) | D19: 0.15

Sheet Planejamento de Férias
B2: ✈️ PLANEJAMENTO DE FÉRIAS
B5: CONFIGURAÇÕES E PARÂMETROS | E5: RESULTADOS CHAVE
B6: Meta do Custo Total da Viagem | C6: 15000 | E6: Quanto guardar por mês? | F6: =PMT(C8, C7, 0, -C6) -> 1195.9494
B7: Meses até as Férias | C7: 12 | E7: Comprometimento do Salário | F7: =F6/C9 -> 0.23918988
B8: Rendimento Mensal (%) | C8: 0.008
B9: Salário do Usuário | C9: 5000
B12: SIMULAÇÃO POR DESTINO
B13: Destino | C13: Custo Estimado | D13: Aporte Mensal Necessário
B14: Praia Nacional | C14: 5000 | D14: =PMT($C$8, $C$7, 0, -C14) -> 398.6498
B15: América do Sul | C15: 10000 | D15: =PMT($C$8, $C$7, 0, -C15) -> 797.2996
B16: Europa | C16: 25000 | D16: =PMT($C$8, $C$7, 0, -C16) -> 1993.249
